Flask_Wizard-0.1.1.dist-info/DESCRIPTION.rst
Flask_Wizard-0.1.1.dist-info/METADATA
Flask_Wizard-0.1.1.dist-info/RECORD
Flask_Wizard-0.1.1.dist-info/WHEEL
Flask_Wizard-0.1.1.dist-info/dependency_links.txt
Flask_Wizard-0.1.1.dist-info/entry_points.txt
Flask_Wizard-0.1.1.dist-info/metadata.json
Flask_Wizard-0.1.1.dist-info/top_level.txt
flask_wizard/__init__.py
flask_wizard/core.py
flask_wizard/facebook.py
flask_wizard/learn.py
flask_wizard/nlu.py
flask_wizard/temp.py
flask_wizard/web.py
flask_wizard_cli/__init__.py
flask_wizard_cli/command_line.py
