Metadata-Version: 2.0
Name: Flask-Wizard
Version: 0.1.1
Summary: Rapid and easy bot development in Python
Home-page: https://github.com/ozzai/flask-wizard
Author: Akshay Kulkarni
Author-email: akshay@ozz.ai
License: Apache 2.0
Platform: any
Classifier: License :: OSI Approved :: Apache Software License
Classifier: Framework :: Flask
Classifier: Programming Language :: Python
Classifier: Environment :: Web Environment
Classifier: Intended Audience :: Developers
Classifier: Operating System :: OS Independent
Classifier: Topic :: Internet :: WWW/HTTP :: Dynamic Content
Classifier: Topic :: Software Development :: Libraries :: Python Modules
Requires-Dist: Flask
